astsearch.py
astsearch-0.2.0.dist-info/entry_points.txt
astsearch-0.2.0.dist-info/WHEEL
astsearch-0.2.0.dist-info/METADATA
astsearch-0.2.0.dist-info/RECORD
